dosh_core/__init__.py
dosh_core/commands/__init__.py
dosh_core/commands/base.py
dosh_core/commands/external.py
dosh_core/commands/internal.py
dosh_core/config.py
dosh_core/environments.py
dosh_core/injections.py
dosh_core/logger.py
dosh_core/lua_runtime.py
dosh_core-0.3.3.dist-info/LICENSE.md
dosh_core-0.3.3.dist-info/METADATA
dosh_core-0.3.3.dist-info/WHEEL
dosh_core-0.3.3.dist-info/RECORD
