Metadata-Version: 2.1
Name: dosh-core
Version: 0.3.3
Summary: Shell-independent task management library.
License: MIT
Author: Gökmen Görgen
Author-email: gkmngrgn@gmail.com
Requires-Python: >=3.9,<3.13
Classifier: Environment :: Console
Classifier: Intended Audience :: Developers
Classifier: Intended Audience :: System Administrators
Classifier: License :: OSI Approved :: MIT License
Classifier: Natural Language :: English
Classifier: Operating System :: MacOS
Classifier: Operating System :: Microsoft
Classifier: Operating System :: POSIX :: Linux
Classifier: Programming Language :: Python :: 3
Classifier: Programming Language :: Python :: 3.9
Classifier: Programming Language :: Python :: 3.10
Classifier: Programming Language :: Python :: 3.11
Classifier: Programming Language :: Python :: 3.12
Classifier: Topic :: Software Development :: Build Tools
Requires-Dist: colorlog (>=6.8.0,<7.0.0)
Requires-Dist: lupa (>=2.0,<3.0)
